[
	{
		"cochlea": "M_AMD_OTOF1_L",
		"image_channel": [
			"Apha",
			"Vglut3",
			"IHC_v4b"
		],
		"segmentation_channel": "IHC_v4b",
		"type": "ihc",
		"n_blocks": 6,
		"component_list": [
			3,
			11
		],
		"halo_size": [
			256,
			256,
			128
		],
		"crop_centers": [
			[
				981,
				1326,
				947
			],
			[
				1281,
				731,
				699
			],
			[
				645,
				872,
				377
			],
			[
				614,
				1126,
				1048
			],
			[
				1017,
				453,
				1106
			],
			[
				715,
				37,
				527
			]
		]
	}
]